YoonSuckYall/__init__.py
YoonSuckYall-0.0.1.dist-info/LICENSE
YoonSuckYall-0.0.1.dist-info/METADATA
YoonSuckYall-0.0.1.dist-info/WHEEL
YoonSuckYall-0.0.1.dist-info/top_level.txt
YoonSuckYall-0.0.1.dist-info/RECORD
